tests/__init__.py
tests/test_tester.py
vaibhav_function_tester/__init__.py
vaibhav_function_tester/cli.py
vaibhav_function_tester/tester.py
vaibhav_function_tester-0.2.0.dist-info/LICENSE
vaibhav_function_tester-0.2.0.dist-info/METADATA
vaibhav_function_tester-0.2.0.dist-info/WHEEL
vaibhav_function_tester-0.2.0.dist-info/entry_points.txt
vaibhav_function_tester-0.2.0.dist-info/top_level.txt
vaibhav_function_tester-0.2.0.dist-info/RECORD
