Metadata-Version: 2.1
Name: vaibhav_function_tester
Version: 0.2.0
Summary: A package to test functions with given inputs and expected outputs
Home-page: https://github.com/vaibhav-rokde/function_tester
Author: Vaibhav Rokde
Author-email: vaibhavrokde232@gmail.com
Classifier: Programming Language :: Python :: 3
Classifier: License :: OSI Approved :: MIT License
Classifier: Operating System :: OS Independent
Requires-Python: >=3.6
License-File: LICENSE
